qudida/__init__.py
qudida/__version__.py
qudida-0.0.4.dist-info/LICENSE
qudida-0.0.4.dist-info/METADATA
qudida-0.0.4.dist-info/WHEEL
qudida-0.0.4.dist-info/top_level.txt
qudida-0.0.4.dist-info/RECORD
