Metadata-Version: 2.1
Name: qudida
Version: 0.0.4
Summary: QUick and DIrty Domain Adaptation
Home-page: https://github.com/arsenyinfo/qudida
License: UNKNOWN
Keywords: Machine Learning,Computer Vision
Platform: UNKNOWN
Classifier: Programming Language :: Python
Classifier: Programming Language :: Python :: 3.5
Classifier: Programming Language :: Python :: 3.6
Classifier: Programming Language :: Python :: 3.7
Classifier: Programming Language :: Python :: 3.8
Requires-Python: >=3.5.0
